mackerel.client-0.2.1-py3.7-nspkg.pth
mackerel/client.py
mackerel/host.py
mackerel/runner.py
mackerel.client-0.2.1.dist-info/LICENSE
mackerel.client-0.2.1.dist-info/METADATA
mackerel.client-0.2.1.dist-info/WHEEL
mackerel.client-0.2.1.dist-info/entry_points.txt
mackerel.client-0.2.1.dist-info/namespace_packages.txt
mackerel.client-0.2.1.dist-info/top_level.txt
mackerel.client-0.2.1.dist-info/RECORD
