Metadata-Version: 2.1
Name: mackerel.client
Version: 0.2.1
Summary: Mackerel client implemented by Python.
Home-page: http://github.com/heavenshell/py-mackerel-client
Author: Shinya Ohyanagi
Author-email: sohyanagi@gmail.com
License: BSD
Platform: any
Classifier: Development Status :: 4 - Beta
Classifier: Environment :: Web Environment
Classifier: Intended Audience :: Developers
Classifier: License :: OSI Approved :: BSD License
Classifier: Operating System :: OS Independent
Classifier: Programming Language :: Python
Requires-Dist: requests
Requires-Dist: simplejson
Requires-Dist: click
